classutil/__init__.py
classutil/__main__.py
classutil/data_types.py
classutil/scrape.py
classutil-2.0.3.dist-info/METADATA
classutil-2.0.3.dist-info/WHEEL
classutil-2.0.3.dist-info/top_level.txt
classutil-2.0.3.dist-info/RECORD
