Metadata-Version: 2.1
Name: classutil
Version: 2.0.3
Summary: Classutil scraper for UNSW.
Home-page: https://github.com/lecafard/classutil
Author: tom nguyen
Author-email: hi@tomn.me
License: MIT
Keywords: unsw classutil scraper
Platform: UNKNOWN
Classifier: License :: OSI Approved :: MIT License
Classifier: Programming Language :: Python :: 3
Requires-Python: >=3
Requires-Dist: aiohttp
Requires-Dist: python-dateutil
Requires-Dist: beautifulsoup4
